classdojo/__init__.py
classdojo/classdojo.py
classdojo-0.0.2.dist-info/LICENSE.txt
classdojo-0.0.2.dist-info/METADATA
classdojo-0.0.2.dist-info/WHEEL
classdojo-0.0.2.dist-info/top_level.txt
classdojo-0.0.2.dist-info/RECORD
