Metadata-Version: 2.1
Name: classdojo
Version: 0.0.2
Summary: Tools to get points from the classdojo point system
Home-page: https://github.com/fishbigger/classdojo
Author: Toby Johnson
Author-email: toby.e.m.Johnson@gmail.com
License: MIT
Download-URL: https://pypi.org/project/classdojo/
Keywords: Classdojo,Dojo,Class Points
Platform: UNKNOWN
Requires-Dist: requests (==2.24.0)
